setup.py
proba_distribution/Binomialdistribution.py
proba_distribution/Gaussiandistribution.py
proba_distribution/Generaldistribution.py
proba_distribution/__init__.py
proba_distribution.egg-info/PKG-INFO
proba_distribution.egg-info/SOURCES.txt
proba_distribution.egg-info/dependency_links.txt
proba_distribution.egg-info/not-zip-safe
proba_distribution.egg-info/top_level.txt