Metadata-Version: 1.0
Name: proba-distribution
Version: 0.1
Summary: Gaussian distributions
Home-page: UNKNOWN
Author: Chidi Chukwumezie
Author-email: austinmilan@yahoo.com
License: UNKNOWN
Platform: UNKNOWN
